esmerald_admin/__init__.py
esmerald_admin/application.py
esmerald_admin/py.typed
esmerald_admin/backends/__init__.py
esmerald_admin/backends/base.py
esmerald_admin/backends/edgy/__init__.py
esmerald_admin/backends/edgy/base.py
esmerald_admin/backends/edgy/email.py
esmerald_admin/backends/edgy/username.py
esmerald_admin/backends/saffier/__init__.py
esmerald_admin/backends/saffier/base.py
esmerald_admin/backends/saffier/email.py
esmerald_admin/backends/saffier/username.py
esmerald_admin-0.4.0.dist-info/METADATA
esmerald_admin-0.4.0.dist-info/WHEEL
esmerald_admin-0.4.0.dist-info/licenses/LICENSE
esmerald_admin-0.4.0.dist-info/RECORD
